Workbook

Sheet Simulador
B2: SIMULADOR DE INVESTIMENTO EM FUNDOS IMOBILIÁRIOS (FIIs)
B4: Ferramenta de Planejamento Financeiro, Projeção de Patrimônio e Alocação por Perfil
B6: 1. CONFIGURAÇÕES E DADOS DE ENTRADA | G6: 3. PROJEÇÃO DE PATRIMÔNIO E DIVIDENDOS POR PRAZO
B7: Salário Mensal (R$): | C7: 5000 | G7: Prazo (Anos) | H7: Meses | I7: Total Investido | J7: Patrimônio Acumulado | K7: Rendimento Mensal
B8: Sugestão de Aporte (30%): | C8: =C7*0.3 | G8: 2 | H8: =G8*12 | I8: =H8*$C$9 | J8: =FV($C$11, H8, -$C$9) | K8: =J8*$C$11
B9: Aporte Mensal Utilizado (R$): | C9: 1500 | G9: 5 | H9: =G9*12 | I9: =H9*$C$9 | J9: =FV($C$11, H9, -$C$9) | K9: =J9*$C$11
B10: Prazo da Simulação (Anos): | C10: 10 | G10: 10 | H10: =G10*12 | I10: =H10*$C$9 | J10: =FV($C$11, H10, -$C$9) | K10: =J10*$C$11
B11: Taxa de Rendimento Mensal (%): | C11: 0.008 | G11: 20 | H11: =G11*12 | I11: =H11*$C$9 | J11: =FV($C$11, H11, -$C$9) | K11: =J11*$C$11
B12: Perfil de Investidor: | C12: Moderado | G12: 30 | H12: =G12*12 | I12: =H12*$C$9 | J12: =FV($C$11, H12, -$C$9) | K12: =J12*$C$11
B14: 2. RESULTADOS DA SIMULAÇÃO (RESPOSTAS DE NEGÓCIO)
B15: 1. Aporte Mensal: | C15: =C9
B16: 2. Prazo Total (Anos): | C16: =C10
B17: 3. Taxa de Rendimento Mensal: | C17: =C11
B18: 4. Patrimônio Acumulado (VF): | C18: =FV(C11, C10*12, -C9)
B19: 5. Dividendos Mensais Estimados: | C19: =C18*C11
B21: 4. DIVISÃO DO APORTE POR TIPO DE FUNDO (CHAVE COMPOSTA + PROCV)
B22: Tipo de Fundo Imobiliário | C22: % Alocação | D22: Aporte Mensal (R$) | E22: Patrimônio Alocado
B23: Papel / Recebíveis | C23: =VLOOKUP($C$12&B23, Apoio_Dados!$A$2:$D$19, 4, FALSE) | D23: =$C$9*C23 | E23: =$C$18*C23
B24: Tijolo - Logística | C24: =VLOOKUP($C$12&B24, Apoio_Dados!$A$2:$D$19, 4, FALSE) | D24: =$C$9*C24 | E24: =$C$18*C24
B25: Tijolo - Shopping | C25: =VLOOKUP($C$12&B25, Apoio_Dados!$A$2:$D$19, 4, FALSE) | D25: =$C$9*C25 | E25: =$C$18*C25
B26: Tijolo - Lajes Corporativas | C26: =VLOOKUP($C$12&B26, Apoio_Dados!$A$2:$D$19, 4, FALSE) | D26: =$C$9*C26 | E26: =$C$18*C26
B27: Fundos de Fundos (FOFs) | C27: =VLOOKUP($C$12&B27, Apoio_Dados!$A$2:$D$19, 4, FALSE) | D27: =$C$9*C27 | E27: =$C$18*C27
B28: Agro / Fiagro | C28: =VLOOKUP($C$12&B28, Apoio_Dados!$A$2:$D$19, 4, FALSE) | D28: =$C$9*C28 | E28: =$C$18*C28
B29: TOTAL | C29: =SUM(C23:C28) | D29: =SUM(D23:D28) | E29: =SUM(E23:E28)

Sheet Apoio_Dados
A1: Chave Composta | B1: Perfil | C1: Tipo de Fundo | D1: Percentual
A2: =B2&C2 | B2: Conservador | C2: Papel / Recebíveis | D2: 0.4
A3: =B3&C3 | B3: Conservador | C3: Tijolo - Logística | D3: 0.25
A4: =B4&C4 | B4: Conservador | C4: Tijolo - Shopping | D4: 0.15
A5: =B5&C5 | B5: Conservador | C5: Tijolo - Lajes Corporativas | D5: 0.05
A6: =B6&C6 | B6: Conservador | C6: Fundos de Fundos (FOFs) | D6: 0.1
A7: =B7&C7 | B7: Conservador | C7: Agro / Fiagro | D7: 0.05
A8: =B8&C8 | B8: Moderado | C8: Papel / Recebíveis | D8: 0.25
A9: =B9&C9 | B9: Moderado | C9: Tijolo - Logística | D9: 0.25
A10: =B10&C10 | B10: Moderado | C10: Tijolo - Shopping | D10: 0.2
A11: =B11&C11 | B11: Moderado | C11: Tijolo - Lajes Corporativas | D11: 0.1
A12: =B12&C12 | B12: Moderado | C12: Fundos de Fundos (FOFs) | D12: 0.1
A13: =B13&C13 | B13: Moderado | C13: Agro / Fiagro | D13: 0.1
... A19: =B19&C19 | B19: Arrojado | C19: Agro / Fiagro | D19: 0.2
